{
    "name": "Your Codespace Name",
    "dockerFile": "Dockerfile",
    "extensions": [
        "GitHub.copilot"
    ],
    "settings": {
        "terminal.integrated.shell.linux": "/bin/bash"
    },
    "postCreateCommand": "echo '# Writing code upon codespace creation!' >> codespace.md",
    "customizations": {
        "vscode": {
            "extensions": [
                "GitHub.copilot"
            ]
        },
        "codespaces": {
            "openFiles": [
                "codespace.md"
            ]
        }
    }
}
